pypillometry/__init__.py
pypillometry/baseline.py
pypillometry/convenience.py
pypillometry/erpd.py
pypillometry/fakedata.py
pypillometry/io.py
pypillometry/preproc.py
pypillometry/pupil.py
pypillometry/pupildata.py
pypillometry/tests/__init__.py
pypillometry/tests/test_io.py
pypillometry/tests/test_pdata.py
pypillometry/tests/test_pupil.py
pypillometry-1.0.3.1.dist-info/LICENSE
pypillometry-1.0.3.1.dist-info/METADATA
pypillometry-1.0.3.1.dist-info/WHEEL
pypillometry-1.0.3.1.dist-info/top_level.txt
pypillometry-1.0.3.1.dist-info/RECORD
