Metadata-Version: 2.1
Name: pypillometry
Version: 1.0.3.1
Summary: Pupillometry in Python.
Home-page: https://github.com/ihrke/pypillometry
Author: Matthias Mittner
Author-email: matthias.mittner@uit.no
License: UNKNOWN
Platform: UNKNOWN
Classifier: Programming Language :: Python :: 3
Classifier: License :: OSI Approved :: MIT License
Classifier: Operating System :: OS Independent
Requires-Python: >=3.6
Requires-Dist: numpy
Requires-Dist: scipy
Requires-Dist: pystan
Requires-Dist: matplotlib
Requires-Dist: pandas
Requires-Dist: typing
Requires-Dist: requests
